square/__init__.py
square/square_formula.py
tests/__init__.py
tests/test_square_formula.py
square_vilavr-0.1.0.dist-info/METADATA
square_vilavr-0.1.0.dist-info/WHEEL
square_vilavr-0.1.0.dist-info/top_level.txt
square_vilavr-0.1.0.dist-info/RECORD
