Metadata-Version: 2.1
Name: square-vilavr
Version: 0.1.0
Summary: A simple package that calculates the square of the sum of two numbers
Author: Your Name
